MANIFEST.in
README.md
setup.py
splunk_sdk.egg-info/PKG-INFO
splunk_sdk.egg-info/SOURCES.txt
splunk_sdk.egg-info/dependency_links.txt
splunk_sdk.egg-info/requires.txt
splunk_sdk.egg-info/top_level.txt
splunklib/__init__.py
splunklib/binding.py
splunklib/client.py
splunklib/data.py
splunklib/results.py
splunklib/six.py
splunklib/utils.py
splunklib/modularinput/__init__.py
splunklib/modularinput/argument.py
splunklib/modularinput/event.py
splunklib/modularinput/event_writer.py
splunklib/modularinput/input_definition.py
splunklib/modularinput/scheme.py
splunklib/modularinput/script.py
splunklib/modularinput/utils.py
splunklib/modularinput/validation_definition.py
splunklib/searchcommands/__init__.py
splunklib/searchcommands/decorators.py
splunklib/searchcommands/environment.py
splunklib/searchcommands/eventing_command.py
splunklib/searchcommands/external_search_command.py
splunklib/searchcommands/generating_command.py
splunklib/searchcommands/internals.py
splunklib/searchcommands/reporting_command.py
splunklib/searchcommands/search_command.py
splunklib/searchcommands/streaming_command.py
splunklib/searchcommands/validators.py